spir/__init__.py
spir/cli.py
spir/convert.py
spir/validate.py
spir/dialects/__init__.py
spir/dialects/alphafold3.py
spir/dialects/alphafold3_server.py
spir/dialects/base.py
spir/dialects/boltz2.py
spir/dialects/chai1.py
spir/dialects/protenix.py
spir/img/logo.png
spir/io/__init__.py
spir/io/csv.py
spir/io/fasta.py
spir/io/json.py
spir/io/yaml.py
spir/ir/__init__.py
spir/ir/ids.py
spir/ir/models.py
spir/ir/normalize.py
spir/ir/glycans/__init__.py
spir/ir/glycans/parse_af3_server.py
spir/ir/glycans/parse_chai.py
spir/ir/glycans/render_af3_server.py
spir/ir/glycans/render_chai.py
spir/ir/glycans/resolve_linkages.py
spir-0.3.0.dist-info/METADATA
spir-0.3.0.dist-info/WHEEL
spir-0.3.0.dist-info/entry_points.txt
spir-0.3.0.dist-info/licenses/LICENSE
spir-0.3.0.dist-info/RECORD
