Metadata-Version: 2.4
Name: spir
Version: 0.3.0
Summary: Intermediate representation and converters for protein folding model inputs
License: MIT
License-File: LICENSE
Requires-Python: >=3.10
Requires-Dist: pydantic>=2.7
Requires-Dist: pyyaml>=6.0
Requires-Dist: typer>=0.20
Provides-Extra: bio
Requires-Dist: biopython>=1.83; extra == 'bio'
Provides-Extra: dev
Requires-Dist: mypy>=1.10; extra == 'dev'
Requires-Dist: pytest>=8; extra == 'dev'
Requires-Dist: ruff>=0.6; extra == 'dev'
